pedrusko_operacoes_ifpb2024/__init__.py
pedrusko_operacoes_ifpb2024/pedrusko_operacoes_ifpb2024.py
pedrusko_operacoes_ifpb2024-0.1.dist-info/METADATA
pedrusko_operacoes_ifpb2024-0.1.dist-info/WHEEL
pedrusko_operacoes_ifpb2024-0.1.dist-info/top_level.txt
pedrusko_operacoes_ifpb2024-0.1.dist-info/RECORD
