Metadata-Version: 2.1
Name: pedrusko-operacoes-ifpb2024
Version: 0.1
Summary: Pacote de operações matemáticas básicas
Home-page: UNKNOWN
Author: Pedro Sávio
Author-email: pedro.sarmento@academico.ifpb.edu.br
License: UNKNOWN
Platform: UNKNOWN
Classifier: Programming Language :: Python :: 3
Classifier: License :: OSI Approved :: MIT License
Classifier: Operating System :: OS Independent
Requires-Python: >=3.6
